ShuziYouminBuluoBoke20162020Fix1/README.md
ShuziYouminBuluoBoke20162020Fix1/__init__.py
ShuziYouminBuluoBoke20162020Fix1/__main__.py
ShuziYouminBuluoBoke20162020Fix1/file.epub
ShuziYouminBuluoBoke20162020Fix1/index.html
ShuziYouminBuluoBoke20162020Fix1/css/__init__.py
ShuziYouminBuluoBoke20162020Fix1/css/annotations.css
ShuziYouminBuluoBoke20162020Fix1/css/main.css
ShuziYouminBuluoBoke20162020Fix1/css/normalize.css
ShuziYouminBuluoBoke20162020Fix1/css/popup.css
ShuziYouminBuluoBoke20162020Fix1/font/__init__.py
ShuziYouminBuluoBoke20162020Fix1/font/fontello.eot
ShuziYouminBuluoBoke20162020Fix1/font/fontello.svg
ShuziYouminBuluoBoke20162020Fix1/font/fontello.ttf
ShuziYouminBuluoBoke20162020Fix1/font/fontello.woff
ShuziYouminBuluoBoke20162020Fix1/img/__init__.py
ShuziYouminBuluoBoke20162020Fix1/img/annotator-glyph-sprite.png
ShuziYouminBuluoBoke20162020Fix1/img/annotator-icon-sprite.png
ShuziYouminBuluoBoke20162020Fix1/img/apple-touch-icon.png
ShuziYouminBuluoBoke20162020Fix1/img/cancelfullscreen.png
ShuziYouminBuluoBoke20162020Fix1/img/close.png
ShuziYouminBuluoBoke20162020Fix1/img/fullscreen.png
ShuziYouminBuluoBoke20162020Fix1/img/loader.gif
ShuziYouminBuluoBoke20162020Fix1/img/menu-icon.png
ShuziYouminBuluoBoke20162020Fix1/img/save.png
ShuziYouminBuluoBoke20162020Fix1/img/saved.png
ShuziYouminBuluoBoke20162020Fix1/img/settings-s.png
ShuziYouminBuluoBoke20162020Fix1/img/settings.png
ShuziYouminBuluoBoke20162020Fix1/img/star.png
ShuziYouminBuluoBoke20162020Fix1/js/__init__.py
ShuziYouminBuluoBoke20162020Fix1/js/epub.js
ShuziYouminBuluoBoke20162020Fix1/js/epub.min.js
ShuziYouminBuluoBoke20162020Fix1/js/epub.min.map
ShuziYouminBuluoBoke20162020Fix1/js/hooks.min.js
ShuziYouminBuluoBoke20162020Fix1/js/hooks.min.map
ShuziYouminBuluoBoke20162020Fix1/js/reader.js
ShuziYouminBuluoBoke20162020Fix1/js/reader.js.map
ShuziYouminBuluoBoke20162020Fix1/js/reader.min.js
ShuziYouminBuluoBoke20162020Fix1/js/reader.min.map
ShuziYouminBuluoBoke20162020Fix1/js/hooks/__init__.py
shuzi_youmin_buluo_boke_2016_2020_fix1-2025.3.25.1.dist-info/METADATA
shuzi_youmin_buluo_boke_2016_2020_fix1-2025.3.25.1.dist-info/WHEEL
shuzi_youmin_buluo_boke_2016_2020_fix1-2025.3.25.1.dist-info/entry_points.txt
shuzi_youmin_buluo_boke_2016_2020_fix1-2025.3.25.1.dist-info/top_level.txt
shuzi_youmin_buluo_boke_2016_2020_fix1-2025.3.25.1.dist-info/RECORD
